django_environments-1.0a4.data/scripts/create_apache_vhost_conf
django_environments-1.0a4.data/scripts/create_apache_vhost_conf.sh
django_environments-1.0a4.data/scripts/deinitenv_generic
django_environments-1.0a4.data/scripts/deinitenv_generic.sh
django_environments-1.0a4.data/scripts/djenv.mercurial
django_environments-1.0a4.data/scripts/djenv.mercurial.sh
django_environments-1.0a4.data/scripts/djenvlib
django_environments-1.0a4.data/scripts/djenvlib.sh
django_environments-1.0a4.data/scripts/initenv_example
django_environments-1.0a4.data/scripts/run_in_env_wrapper
django_environments-1.0a4.data/scripts/run_in_env_wrapper.sh
django_environments-1.0a4.data/scripts/set_permissions
django_environments-1.0a4.data/scripts/set_permissions.sh
django_environments-1.0a4.dist-info/DESCRIPTION.rst
django_environments-1.0a4.dist-info/METADATA
django_environments-1.0a4.dist-info/metadata.json
django_environments-1.0a4.dist-info/RECORD
django_environments-1.0a4.dist-info/top_level.txt
django_environments-1.0a4.dist-info/WHEEL
djenv/__init__.py
djenv/_version.py
djenv/urls.py
djenv/settings/__init__.py
djenv/settings/cache.py
djenv/settings/core.py
djenv/settings/database.py
djenv/settings/generic.py
djenv/settings/log.py
djenv/settings/template.py
djenv/settings/apps/__init__.py
djenv/settings/apps/compressor.py
djenv/settings/apps/rosetta.py
